[
    {
        "name": "Enablement Platform",
        "cluster": "Бизнес платформы"
    },
    {
        "name": "Websso (Identity)",
        "cluster": "Бизнес платформы"
    },
    {
        "name": "Биометрия",
        "cluster": "Бизнес платформы"
    },
    {
        "name": "MTC Premium",
        "cluster": "Бизнес платформы"
    },
    {
        "name": "UMS (Unified Messaging System)",
        "cluster": "Бизнес платформы"
    },
    {
        "name": "RTM",
        "cluster": "Бизнес платформы"
    },
    {
        "name": "eSIM Watch",
        "cluster": "Бизнес платформы"
    },
    {
        "name": "Fingate",
        "cluster": "Бизнес платформы"
    },
    {
        "name": "Аметист",
        "cluster": "Бизнес платформы"
    },
    {
        "name": "Coworking",
        "cluster": "Бизнес платформы"
    },
    {
        "name": "IoT Connected Car",
        "cluster": "Бизнес платформы"
    },
    {
        "name": "MTS Junior",
        "cluster": "Бизнес платформы"
    },
    {
        "name": "Product Factory ",
        "cluster": "Технологические платформы"
    },
    {
        "name": "Интеграционная платформа",
        "cluster": "Технологические платформы"
    },
    {
        "name": "Платформа тестирования",
        "cluster": "Технологические платформы"
    },
    {
        "name": "Selfe",
        "cluster": "Технологические платформы"
    },
    {
        "name": "Витрина Качества ИТ",
        "cluster": "Технологические платформы"
    },
    {
        "name": "Платформа ITSM",
        "cluster": "Технологические платформы"
    },
    {
        "name": "RMS",
        "cluster": "Технологические платформы"
    },
    {
        "name": "Da Vinci",
        "cluster": "Технологические платформы"
    },
    {
        "name": "Timesheets 2.0",
        "cluster": "Технологические платформы"
    },
    {
        "name": "SAM 2.0",
        "cluster": "Технологические платформы"
    },
    {
        "name": "Платформа IMS",
        "cluster": "Технологические платформы"
    },
    {
        "name": "Платформа мониторинга и наблюдаемости 2.0",
        "cluster": "Технологические платформы"
    },
    {
        "name": "Compliance Hub",
        "cluster": "Корпоративные сервисы"
    },
    {
        "name": "MTS Doks",
        "cluster": "Корпоративные сервисы"
    },
    {
        "name": "Shield",
        "cluster": "Корпоративные сервисы"
    },
    {
        "name": "Blink",
        "cluster": "Корпоративные сервисы"
    },
    {
        "name": "Pepper Potts",
        "cluster": "Корпоративные сервисы"
    },
    {
        "name": "Xavier",
        "cluster": "Корпоративные сервисы"
    },
    {
        "name": "RPA",
        "cluster": "Корпоративные сервисы"
    },
    {
        "name": "Jocasta",
        "cluster": "Корпоративные сервисы"
    },
    {
        "name": "FCM",
        "cluster": "Корпоративные сервисы"
    },
    {
        "name": "HP OPEX",
        "cluster": "Корпоративные сервисы"
    },
    {
        "name": "Project BI",
        "cluster": "Корпоративные сервисы"
    },
    {
        "name": "СХД ЕЦО+HR",
        "cluster": "Корпоративные сервисы"
    },
    {
        "name": "LD",
        "cluster": "Корпоративные сервисы"
    },
    {
        "name": "FMS",
        "cluster": "Корпоративные сервисы"
    },
    {
        "name": "LMS",
        "cluster": "Корпоративные сервисы"
    },
    {
        "name": "SCP",
        "cluster": "Корпоративные сервисы"
    },
    {
        "name": "JDE",
        "cluster": "Корпоративные сервисы"
    },
    {
        "name": "ССД ВРМ",
        "cluster": "Корпоративные сервисы"
    },
    {
        "name": "Blog",
        "cluster": "Корпоративные сервисы"
    },
    {
        "name": "ESON The Searcher",
        "cluster": "Корпоративные сервисы"
    },
    {
        "name": "HRGate",
        "cluster": "Корпоративные сервисы"
    },
    {
        "name": "АСУЭП",
        "cluster": "Корпоративные сервисы"
    },
    {
        "name": "Colossus",
        "cluster": "Корпоративные сервисы"
    },
    {
        "name": "Hello",
        "cluster": "Корпоративные сервисы"
    },
    {
        "name": "Beast ",
        "cluster": "Корпоративные сервисы"
    },
    {
        "name": "Портал МГМНВЗ",
        "cluster": "Корпоративные сервисы"
    },
    {
        "name": "Телепорт",
        "cluster": "Корпоративные сервисы"
    },
    {
        "name": "ServiceDesk",
        "cluster": "Корпоративные сервисы"
    },
    {
        "name": "PPInfo",
        "cluster": "Корпоративные сервисы"
    },
    {
        "name": "iDA",
        "cluster": "Корпоративные сервисы"
    },
    {
        "name": "TMS",
        "cluster": "Корпоративные сервисы"
    },
    {
        "name": "Dopinder",
        "cluster": "Корпоративные сервисы"
    },
    {
        "name": "3click",
        "cluster": "Корпоративные сервисы"
    },
    {
        "name": "1С Ядро",
        "cluster": "Корпоративные сервисы"
    },
    {
        "name": "HFM",
        "cluster": "Корпоративные сервисы"
    },
    {
        "name": "Power BI_Finportal",
        "cluster": "Корпоративные сервисы"
    },
    {
        "name": "Dashboard HR",
        "cluster": "Корпоративные сервисы"
    },
    {
        "name": "ProCube",
        "cluster": "Корпоративные сервисы"
    },
    {
        "name": "Dashboard Working Capital",
        "cluster": "Корпоративные сервисы"
    },
    {
        "name": "TAX BI",
        "cluster": "Корпоративные сервисы"
    },
    {
        "name": "PM BI",
        "cluster": "Корпоративные сервисы"
    },
    {
        "name": "HRMS",
        "cluster": "Корпоративные сервисы"
    },
    {
        "name": "OEBS Логистика",
        "cluster": "Корпоративные сервисы"
    },
    {
        "name": "OEBS Кадры",
        "cluster": "Корпоративные сервисы"
    },
    {
        "name": "OEBS Финансы",
        "cluster": "Корпоративные сервисы"
    },
    {
        "name": "OEBS",
        "cluster": "Корпоративные сервисы"
    },
    {
        "name": "RocketChat",
        "cluster": "Корпоративные сервисы"
    },
    {
        "name": "Корпоративная телефония",
        "cluster": "Корпоративные сервисы"
    },
    {
        "name": "Cisco WebEx",
        "cluster": "Корпоративные сервисы"
    },
    {
        "name": "LDAP",
        "cluster": "Корпоративные сервисы"
    },
    {
        "name": "Платформы дистанционной работы",
        "cluster": "Корпоративные сервисы"
    },
    {
        "name": "Платформа пользовательского технологического обмена и хранения данных (FS)",
        "cluster": "Корпоративные сервисы"
    },
    {
        "name": "NextCloud",
        "cluster": "Корпоративные сервисы"
    },
    {
        "name": "sFTP",
        "cluster": "Корпоративные сервисы"
    },
    {
        "name": "1C:Предприятие Управление торговлей",
        "cluster": "Корпоративные сервисы"
    },
    {
        "name": "OIM",
        "cluster": "Корпоративные сервисы"
    },
    {
        "name": "Одно Окно",
        "cluster": "Корпоративные сервисы"
    },
    {
        "name": "Система видеовещания video-online",
        "cluster": "Корпоративные сервисы"
    },
    {
        "name": "Автоматизированная система учёта лицензий SoftStat",
        "cluster": "Корпоративные сервисы"
    },
    {
        "name": "Программное обеспечение рабочих мест",
        "cluster": "Корпоративные сервисы"
    },
    {
        "name": "Сервисное сопровождение продуктов ЦУПО",
        "cluster": "Корпоративные сервисы"
    },
    {
        "name": "Управление программным обеспечением рабочих мест",
        "cluster": "Корпоративные сервисы"
    },
    {
        "name": "Управление программным обеспечением серверов",
        "cluster": "Корпоративные сервисы"
    },
    {
        "name": "СЭД «Босс-Референт»",
        "cluster": "Корпоративные сервисы"
    },
    {
        "name": "Корпоративная почта (Ms Exchange Outlook)",
        "cluster": "Корпоративные сервисы"
    },
    {
        "name": "Skype for business (Система корпоративных коммуникаций)",
        "cluster": "Корпоративные сервисы"
    },
    {
        "name": "Система журналирования и архивирования почтовых сообщений (EMC Source One)",
        "cluster": "Корпоративные сервисы"
    },
    {
        "name": "Портал СКР",
        "cluster": "Корпоративные сервисы"
    },
    {
        "name": "Доступ в интернет",
        "cluster": "Корпоративные сервисы"
    },
    {
        "name": "Active Directory",
        "cluster": "Корпоративные сервисы"
    },
    {
        "name": "Личный кабинет BPM (Eludia)",
        "cluster": "Корпоративные сервисы"
    },
    {
        "name": "Локальная поддержка",
        "cluster": "Корпоративные сервисы"
    },
    {
        "name": "Виртуальное рабочее место",
        "cluster": "Корпоративные сервисы"
    },
    {
        "name": "ИС Централизованный Клиринг",
        "cluster": "Корпоративные сервисы"
    },
    {
        "name": "Экспертное ИТ-обслуживание пользователей",
        "cluster": "Корпоративные сервисы"
    },
    {
        "name": "Физическое рабочее место",
        "cluster": "Корпоративные сервисы"
    },
    {
        "name": "Управление активами рабочих мест",
        "cluster": "Корпоративные сервисы"
    },
    {
        "name": "Сервисы дистанционной работы (VPN, Citrix Netscaler, EMM)",
        "cluster": "Корпоративные сервисы"
    },
    {
        "name": "Сервис потокового сканирования",
        "cluster": "Корпоративные сервисы"
    },
    {
        "name": "Сервис поддержки СКС и СЭС",
        "cluster": "Корпоративные сервисы"
    },
    {
        "name": "Сервис печати и копирования",
        "cluster": "Корпоративные сервисы"
    },
    {
        "name": "Настройка и управление инфраструктурой РМ",
        "cluster": "Корпоративные сервисы"
    },
    {
        "name": "Мультиплатформенное рабочее место (non-Win)",
        "cluster": "Корпоративные сервисы"
    },
    {
        "name": "Мониторинг и Аналитика Рабочих Мест",
        "cluster": "Корпоративные сервисы"
    },
    {
        "name": "Интеграция дочерних организаций в ИТ инфраструктуру МТС",
        "cluster": "Корпоративные сервисы"
    },
    {
        "name": "VIP",
        "cluster": "Корпоративные сервисы"
    },
    {
        "name": "Location Pro",
        "cluster": "Умный дом и IoT"
    },
    {
        "name": "Vibrolog (Вибродиагностика)",
        "cluster": "Умный дом и IoT"
    },
    {
        "name": "Smart click (Умная кнопка)",
        "cluster": "Умный дом и IoT"
    },
    {
        "name": "Цифровой водоканал",
        "cluster": "Умный дом и IoT"
    },
    {
        "name": "МТС IoT HUB",
        "cluster": "Умный дом и IoT"
    },
    {
        "name": "Поиск коммерческих потерь в электрических сетях (EnergyTool)",
        "cluster": "Умный дом и IoT"
    },
    {
        "name": "Цельсиум (I датчик)",
        "cluster": "Умный дом и IoT"
    },
    {
        "name": "Умный замок (Smart Lock)",
        "cluster": "Умный дом и IoT"
    },
    {
        "name": "МТС Гольфстрим / МТС Smart Home",
        "cluster": "Умный дом и IoT"
    },
    {
        "name": "Цифровая недвижимость",
        "cluster": "Умный дом и IoT"
    },
    {
        "name": "МТС Safe Zone",
        "cluster": "Умный дом и IoT"
    },
    {
        "name": "Siebel",
        "cluster": "CX"
    },
    {
        "name": "BI отчетность Siebel",
        "cluster": "CX"
    },
    {
        "name": "YandexSupportAI",
        "cluster": "CX"
    },
    {
        "name": "OMNIChat",
        "cluster": "CX"
    },
    {
        "name": "Интеграционный слой Siebel - Weblogic",
        "cluster": "CX"
    },
    {
        "name": "Система Управления Знаниями (СУЗ)",
        "cluster": "CX"
    },
    {
        "name": "Ringer",
        "cluster": "CX"
    },
    {
        "name": "Seldon.Doc (BigDoc)",
        "cluster": "CX"
    },
    {
        "name": "Конфигуратор продуктов B2B",
        "cluster": "CX"
    },
    {
        "name": "Модуль Public API",
        "cluster": "CX"
    },
    {
        "name": "CFSS - Автоматический опрос (GENESYS)",
        "cluster": "CX"
    },
    {
        "name": "Защитник **",
        "cluster": "CX"
    },
    {
        "name": "VBot (Голосовой помощник Customer Service helper)",
        "cluster": "CX"
    },
    {
        "name": "Автоматическое информирование (Рупор)",
        "cluster": "CX"
    },
    {
        "name": "МТС Connect Wizard",
        "cluster": "CX"
    },
    {
        "name": "Будь лучше",
        "cluster": "CX"
    },
    {
        "name": "Customer Communication Platform (CX.CC)",
        "cluster": "CX"
    },
    {
        "name": "CJ Monitoring and Discovery",
        "cluster": "CX"
    },
    {
        "name": "Инсорсинг Контактный Центр",
        "cluster": "CX"
    },
    {
        "name": "Fraud Detection Platform",
        "cluster": "Телеком"
    },
    {
        "name": "GR Canal",
        "cluster": "Телеком"
    },
    {
        "name": "BrandSafety (Trademark System)",
        "cluster": "Телеком"
    },
    {
        "name": "Internal Crawler",
        "cluster": "Телеком"
    },
    {
        "name": "RM.MA (Revenue Management. Margin Assurance)",
        "cluster": "Телеком"
    },
    {
        "name": "MTS Smartdocs",
        "cluster": "Телеком"
    },
    {
        "name": "RM.RA (Revenue Management. Revenue Assurance)",
        "cluster": "Телеком"
    },
    {
        "name": "АСР FORIS",
        "cluster": "Телеком"
    },
    {
        "name": "Дилерский Портал ФС (УРМД фикс)",
        "cluster": "Телеком"
    },
    {
        "name": "Среда ЭДО",
        "cluster": "Телеком"
    },
    {
        "name": "АСР Расчеты",
        "cluster": "Телеком"
    },
    {
        "name": "Dealer Life",
        "cluster": "Телеком"
    },
    {
        "name": "МТС Партнер",
        "cluster": "Телеком"
    },
    {
        "name": "Платформа Партнерских Отношений (ППО)",
        "cluster": "Телеком"
    },
    {
        "name": "Medio AS/OCS",
        "cluster": "Телеком"
    },
    {
        "name": "Rating & Decision Making (RDM)",
        "cluster": "Телеком"
    },
    {
        "name": "Automation of Sales B2B",
        "cluster": "Телеком"
    },
    {
        "name": "ШПД (B2B фикс.)",
        "cluster": "Телеком"
    },
    {
        "name": "Connectivity-as-a-Service (Wi-Fi для бизнеса)",
        "cluster": "Телеком"
    },
    {
        "name": "ГеоЭффект",
        "cluster": "Телеком"
    },
    {
        "name": "Личный кабинет МТС Бизнес",
        "cluster": "Телеком"
    },
    {
        "name": "МТС Облачное видеонаблюдение",
        "cluster": "Телеком"
    },
    {
        "name": "Hexagon LCR",
        "cluster": "Телеком"
    },
    {
        "name": "Портал запуска маркетинговых программ",
        "cluster": "Телеком"
    },
    {
        "name": "RedPack",
        "cluster": "Телеком"
    },
    {
        "name": "Интерконнект ITC",
        "cluster": "Телеком"
    },
    {
        "name": "Fix House",
        "cluster": "Телеком"
    },
    {
        "name": "OPS Tools",
        "cluster": "Телеком"
    },
    {
        "name": "Telecom Mediation",
        "cluster": "Телеком"
    },
    {
        "name": "Инструменты продаж Online Sales",
        "cluster": "Телеком"
    },
    {
        "name": "Service Delivery Platform (SDP)",
        "cluster": "Телеком"
    },
    {
        "name": "RTDMS.GEO",
        "cluster": "Развитие инфраструктуры"
    },
    {
        "name": "RTDMS.UPT",
        "cluster": "Развитие инфраструктуры"
    },
    {
        "name": "КЕДР",
        "cluster": "Развитие инфраструктуры"
    },
    {
        "name": "NPM.Transport",
        "cluster": "Развитие инфраструктуры"
    },
    {
        "name": "NPM.Backbone",
        "cluster": "Развитие инфраструктуры"
    },
    {
        "name": "CQM",
        "cluster": "Развитие инфраструктуры"
    },
    {
        "name": "Inetcore",
        "cluster": "Развитие инфраструктуры"
    },
    {
        "name": "Virtual Infrastructure",
        "cluster": "Облачная платформа"
    },
    {
        "name": "Защищенные сегменты",
        "cluster": "Облачная платформа"
    },
    {
        "name": "GPU в облаке",
        "cluster": "Облачная платформа"
    },
    {
        "name": "Контейнерные технологии",
        "cluster": "Облачная платформа"
    },
    {
        "name": "Хостинг 1С",
        "cluster": "Облачная платформа"
    },
    {
        "name": "Резервное копирование",
        "cluster": "Облачная платформа"
    },
    {
        "name": "Катастрофоустойчивая инфраструктура и миграция",
        "cluster": "Облачная платформа"
    },
    {
        "name": "Хранение данных: объектное хранилище и архивирование",
        "cluster": "Облачная платформа"
    },
    {
        "name": "Облачный роутер",
        "cluster": "Облачная платформа"
    },
    {
        "name": "Распределенный балансировщик нагрузки",
        "cluster": "Облачная платформа"
    },
    {
        "name": "SD-WAN",
        "cluster": "Облачная платформа"
    },
    {
        "name": "CDN – перепродажа чужого CDN",
        "cluster": "Облачная платформа"
    },
    {
        "name": "WAF – файрвол уровня приложений",
        "cluster": "Облачная платформа"
    },
    {
        "name": "AntiDDOS",
        "cluster": "Облачная платформа"
    },
    {
        "name": "Облачный ГостVPN",
        "cluster": "Облачная платформа"
    },
    {
        "name": "Антивирусная защита",
        "cluster": "Облачная платформа"
    },
    {
        "name": "SOC – мониторинг и реагирование",
        "cluster": "Облачная платформа"
    },
    {
        "name": "PostgreSQL",
        "cluster": "Облачная платформа"
    },
    {
        "name": "Redis",
        "cluster": "Облачная платформа"
    },
    {
        "name": "Kafka",
        "cluster": "Облачная платформа"
    },
    {
        "name": "BI",
        "cluster": "Облачная платформа"
    },
    {
        "name": "Виртуальное рабочее место",
        "cluster": "Облачная платформа"
    },
    {
        "name": "Почта",
        "cluster": "Облачная платформа"
    },
    {
        "name": "Офис",
        "cluster": "Облачная платформа"
    },
    {
        "name": "Облачный диск",
        "cluster": "Облачная платформа"
    },
    {
        "name": "LDAP+",
        "cluster": "Облачная платформа"
    },
    {
        "name": "Российское ПО в облаке",
        "cluster": "Облачная платформа"
    },
    {
        "name": "Клиентская облачная платформа (сайт)",
        "cluster": "Облачная платформа"
    },
    {
        "name": "Технологическая облачная платформа (CloudHub)",
        "cluster": "Облачная платформа"
    },
    {
        "name": "1Cloud",
        "cluster": "Облачная платформа"
    },
    {
        "name": "Мой МТС",
        "cluster": "Цифровые продукты и партнерства"
    },
    {
        "name": "Calls2CC",
        "cluster": "Цифровые продукты и партнерства"
    },
    {
        "name": "MWVSMM",
        "cluster": "Цифровые продукты и партнерства"
    },
    {
        "name": "Виртуальный номер",
        "cluster": "Цифровые продукты и партнерства"
    },
    {
        "name": "МТС Cashback",
        "cluster": "Цифровые продукты и партнерства"
    },
    {
        "name": "МТС Библиотека",
        "cluster": "Цифровые продукты и партнерства"
    },
    {
        "name": "Master Hub",
        "cluster": "Цифровые продукты и партнерства"
    },
    {
        "name": "Справка",
        "cluster": "Цифровые продукты и партнерства"
    },
    {
        "name": "Обратная связь",
        "cluster": "Цифровые продукты и партнерства"
    },
    {
        "name": "GOODOK",
        "cluster": "Цифровые продукты и партнерства"
    },
    {
        "name": "МТС Music",
        "cluster": "Цифровые продукты и партнерства"
    },
    {
        "name": "МТС Live (МТС Афиша)/VR",
        "cluster": "Цифровые продукты и партнерства"
    },
    {
        "name": "МТС Вторая память",
        "cluster": "Цифровые продукты и партнерства"
    },
    {
        "name": "МТС Лончер",
        "cluster": "Цифровые продукты и партнерства"
    },
    {
        "name": "Мобильный ID",
        "cluster": "Цифровые продукты и партнерства"
    },
    {
        "name": "МТС Опросы",
        "cluster": "Цифровые продукты и партнерства"
    },
    {
        "name": "Дизайн-система",
        "cluster": "Цифровые продукты и партнерства"
    },
    {
        "name": "МТС Закупки",
        "cluster": "Цифровые продукты и партнерства"
    },
    {
        "name": "МТС Агенты",
        "cluster": "Цифровые продукты и партнерства"
    },
    {
        "name": "МТС Партнеры",
        "cluster": "Цифровые продукты и партнерства"
    },
    {
        "name": "МТС Developers",
        "cluster": "Цифровые продукты и партнерства"
    },
    {
        "name": "CMS",
        "cluster": "Цифровые продукты и партнерства"
    },
    {
        "name": "eHealth / Beffo",
        "cluster": "Цифровые продукты и партнерства"
    },
    {
        "name": "Game Center / PriceDrop",
        "cluster": "Цифровые продукты и партнерства"
    },
    {
        "name": "Scan ID / Инсайдер.Pro",
        "cluster": "Цифровые продукты и партнерства"
    },
    {
        "name": "МТС Секретарь",
        "cluster": "Цифровые продукты и партнерства"
    },
    {
        "name": "Cloud Gaming",
        "cluster": "Цифровые продукты и партнерства"
    },
    {
        "name": "Gogym",
        "cluster": "Цифровые продукты и партнерства"
    },
    {
        "name": "Кредитная Карма / FinAdvice",
        "cluster": "Цифровые продукты и партнерства"
    },
    {
        "name": "Виртуальный ассистент",
        "cluster": "Цифровые продукты и партнерства"
    },
    {
        "name": "Умные девайсы Pet",
        "cluster": "Цифровые продукты и партнерства"
    },
    {
        "name": "esports  WASD.tv",
        "cluster": "Цифровые продукты и партнерства"
    },
    {
        "name": "Геоплатформа",
        "cluster": "Цифровые продукты и партнерства"
    },
    {
        "name": "МТС Бизнес",
        "cluster": "Цифровые продукты и партнерства"
    },
    {
        "name": "Ticketland",
        "cluster": "Цифровые продукты и партнерства"
    },
    {
        "name": "Мой МТС Беларусь",
        "cluster": "Цифровые продукты и партнерства"
    },
    {
        "name": "Мой МТС Армения",
        "cluster": "Цифровые продукты и партнерства"
    },
    {
        "name": "Мой МГТС",
        "cluster": "Цифровые продукты и партнерства"
    },
    {
        "name": "Там-Спам",
        "cluster": "Цифровые продукты и партнерства"
    },
    {
        "name": "МТС Поиск",
        "cluster": "Цифровые продукты и партнерства"
    },
    {
        "name": "Умные девайсы Смартопус",
        "cluster": "Цифровые продукты и партнерства"
    },
    {
        "name": "МТС Коннект",
        "cluster": "Цифровые продукты и партнерства"
    },
    {
        "name": "Оптимизация внутренних процессов РТК",
        "cluster": "РТК"
    },
    {
        "name": "Товародвижение и Управление Ассортиментом",
        "cluster": "РТК"
    },
    {
        "name": "Единое окно РТК",
        "cluster": "РТК"
    },
    {
        "name": "Мобильное приложение Мой РТК",
        "cluster": "РТК"
    },
    {
        "name": "WFM РТК (Бэк-офис)",
        "cluster": "РТК"
    },
    {
        "name": "Система расчета премии (НСМ)",
        "cluster": "РТК"
    },
    {
        "name": "BaaS",
        "cluster": "МТС Банк"
    },
    {
        "name": "NUUM",
        "cluster": "МТС Банк"
    },
    {
        "name": "POS-кредитование",
        "cluster": "МТС Банк"
    },
    {
        "name": "POS-кредитование (внутреннее)",
        "cluster": "МТС Банк"
    },
    {
        "name": "Siebel SME",
        "cluster": "МТС Банк"
    },
    {
        "name": "Sistema Wealth",
        "cluster": "МТС Банк"
    },
    {
        "name": "Top Up",
        "cluster": "МТС Банк"
    },
    {
        "name": "Вклады",
        "cluster": "МТС Банк"
    },
    {
        "name": "ВЭД и FX",
        "cluster": "МТС Банк"
    },
    {
        "name": "Гарантии МСБ",
        "cluster": "МТС Банк"
    },
    {
        "name": "Дебетовые карты",
        "cluster": "МТС Банк"
    },
    {
        "name": "Депозиты и остатки МСБ",
        "cluster": "МТС Банк"
    },
    {
        "name": "ДИТ Москвы",
        "cluster": "МТС Банк"
    },
    {
        "name": "ДИТ Регионы",
        "cluster": "МТС Банк"
    },
    {
        "name": "Доставка",
        "cluster": "МТС Банк"
    },
    {
        "name": "Единый сайт Финтех",
        "cluster": "МТС Банк"
    },
    {
        "name": "ЕХД",
        "cluster": "МТС Банк"
    },
    {
        "name": "Клиентский сервис в digital",
        "cluster": "МТС Банк"
    },
    {
        "name": "Залоговое кредитование",
        "cluster": "МТС Банк"
    },
    {
        "name": "Конвергент",
        "cluster": "МТС Банк"
    },
    {
        "name": "Корпоративные карты МСБ",
        "cluster": "МТС Банк"
    },
    {
        "name": "Корпоративный бизнес",
        "cluster": "МТС Банк"
    },
    {
        "name": "Кредитные карты",
        "cluster": "МТС Банк"
    },
    {
        "name": "Кредитный брокер (Finconnect)",
        "cluster": "МТС Банк"
    },
    {
        "name": "Кредитный конвейер",
        "cluster": "МТС Банк"
    },
    {
        "name": "Кредитование МСБ",
        "cluster": "МТС Банк"
    },
    {
        "name": "Личные финансы",
        "cluster": "МТС Банк"
    },
    {
        "name": "Микрокредитование",
        "cluster": "МТС Банк"
    },
    {
        "name": "Мобильная коммерция",
        "cluster": "МТС Банк"
    },
    {
        "name": "МТС Банк (мобильное приложение)",
        "cluster": "МТС Банк"
    },
    {
        "name": "МТС Банк Premium",
        "cluster": "МТС Банк"
    },
    {
        "name": "МТС Банк Бизнес",
        "cluster": "МТС Банк"
    },
    {
        "name": "МТС Инвестиции",
        "cluster": "МТС Банк"
    },
    {
        "name": "МТС Касса",
        "cluster": "МТС Банк"
    },
    {
        "name": "МТС Оплата",
        "cluster": "МТС Банк"
    },
    {
        "name": "МТС-лимит",
        "cluster": "МТС Банк"
    },
    {
        "name": "МТС-рассрочка",
        "cluster": "МТС Банк"
    },
    {
        "name": "НЦПК",
        "cluster": "МТС Банк"
    },
    {
        "name": "Обещанный платеж",
        "cluster": "МТС Банк"
    },
    {
        "name": "Переводы",
        "cluster": "МТС Банк"
    },
    {
        "name": "Платежи",
        "cluster": "МТС Банк"
    },
    {
        "name": "Продукты для нерезидентов",
        "cluster": "МТС Банк"
    },
    {
        "name": "Раздел Финансы в Мой МТС",
        "cluster": "МТС Банк"
    },
    {
        "name": "РКО МСБ",
        "cluster": "МТС Банк"
    },
    {
        "name": "Самозанятые",
        "cluster": "МТС Банк"
    },
    {
        "name": "СБП",
        "cluster": "МТС Банк"
    },
    {
        "name": "Страхование",
        "cluster": "МТС Банк"
    },
    {
        "name": "Устройства самообслуживания",
        "cluster": "МТС Банк"
    },
    {
        "name": "Факторинг",
        "cluster": "МТС Банк"
    },
    {
        "name": "Цифровой рубль",
        "cluster": "МТС Банк"
    },
    {
        "name": "Эквайринг",
        "cluster": "МТС Банк"
    },
    {
        "name": "Siebel CRM",
        "cluster": "МТС Банк"
    },
    {
        "name": "KION",
        "cluster": "МТС Медиа"
    },
    {
        "name": "TV House",
        "cluster": "МТС Медиа"
    },
    {
        "name": "MediaGateway (MGW)",
        "cluster": "МТС Медиа"
    },
    {
        "name": "Знаем Лично",
        "cluster": "Рекламные технологии"
    },
    {
        "name": "Банковский продукт для B2B клиентов",
        "cluster": "Рекламные технологии"
    },
    {
        "name": "МТС Твой Бизнес",
        "cluster": "Рекламные технологии"
    },
    {
        "name": "MTS_DSP - MTS DSP",
        "cluster": "Рекламные технологии"
    },
    {
        "name": "MTS_SSP",
        "cluster": "Рекламные технологии"
    },
    {
        "name": "Оператор Рекламных Данных",
        "cluster": "Рекламные технологии"
    },
    {
        "name": "МТС Маркетолог",
        "cluster": "Рекламные технологии"
    },
    {
        "name": "Медиа-планировщик",
        "cluster": "Рекламные технологии"
    },
    {
        "name": "ChatPoint",
        "cluster": "Рекламные технологии"
    },
    {
        "name": "Платформа мобильной коммерции",
        "cluster": "Рекламные технологии"
    },
    {
        "name": "Партнерская сеть CPA",
        "cluster": "Рекламные технологии"
    },
    {
        "name": "МТС Talent Review",
        "cluster": "Рекламные технологии"
    },
    {
        "name": "Smart Rollout",
        "cluster": "Big Data"
    },
    {
        "name": "Market View",
        "cluster": "Big Data"
    },
    {
        "name": "Golden Record",
        "cluster": "Big Data"
    },
    {
        "name": "RecSys Platform",
        "cluster": "Big Data"
    },
    {
        "name": "Scoring",
        "cluster": "Big Data"
    },
    {
        "name": "Лидогенерация",
        "cluster": "Big Data"
    },
    {
        "name": "Страхование",
        "cluster": "Big Data"
    },
    {
        "name": "Антиспам (SBL+WhCl+a2p-spam)",
        "cluster": "Big Data"
    },
    {
        "name": "Отток B2C",
        "cluster": "Big Data"
    },
    {
        "name": "Предиктивная аналитика продаж",
        "cluster": "Big Data"
    },
    {
        "name": "Smart Reprice",
        "cluster": "Big Data"
    },
    {
        "name": "Фиксированный бизнес B2C",
        "cluster": "Big Data"
    },
    {
        "name": "B2B ОКН",
        "cluster": "Big Data"
    },
    {
        "name": "Лидогенерация и отток B2B",
        "cluster": "Big Data"
    },
    {
        "name": "Неинвазивные методы замера клиентского опыта",
        "cluster": "Big Data"
    },
    {
        "name": "Дашборды по конкурентам",
        "cluster": "Big Data"
    },
    {
        "name": "МТС Карма",
        "cluster": "Big Data"
    },
    {
        "name": "РТК. Динамическое ценообразование",
        "cluster": "Big Data"
    },
    {
        "name": "Рекомендации в личных финансах",
        "cluster": "Big Data"
    },
    {
        "name": "DataOps - ETL Service",
        "cluster": "Big Data"
    },
    {
        "name": "DataOps - Data Quality",
        "cluster": "Big Data"
    },
    {
        "name": "DataOps - Stream Processing",
        "cluster": "Big Data"
    },
    {
        "name": "DataOps - Data Catalog",
        "cluster": "Big Data"
    },
    {
        "name": "DataOps - BI",
        "cluster": "Big Data"
    },
    {
        "name": "DataOps - Data Virtualization",
        "cluster": "Big Data"
    },
    {
        "name": "DataOps - Lake House",
        "cluster": "Big Data"
    },
    {
        "name": "DataOps - RDM",
        "cluster": "Big Data"
    },
    {
        "name": "DataOps - Clickhouse",
        "cluster": "Big Data"
    },
    {
        "name": "DataOps - GreenPlum",
        "cluster": "Big Data"
    },
    {
        "name": "DataOps - Hadoop",
        "cluster": "Big Data"
    },
    {
        "name": "DataOps - Support",
        "cluster": "Big Data"
    },
    {
        "name": "MLOps Platform",
        "cluster": "Big Data"
    },
    {
        "name": "МТС Аналитика",
        "cluster": "Big Data"
    },
    {
        "name": "Scraptor",
        "cluster": "Big Data"
    },
    {
        "name": "Data Lake",
        "cluster": "Big Data"
    },
    {
        "name": "NET",
        "cluster": "Big Data"
    },
    {
        "name": "vData River",
        "cluster": "Big Data"
    },
    {
        "name": "Digital",
        "cluster": "Big Data"
    },
    {
        "name": "ID Scan",
        "cluster": "Big Data"
    },
    {
        "name": "Маркетолог",
        "cluster": "Big Data"
    },
    {
        "name": "КИХ",
        "cluster": "Big Data"
    },
    {
        "name": "БОПОС",
        "cluster": "Big Data"
    },
    {
        "name": "ACOLL",
        "cluster": "Big Data"
    },
    {
        "name": "SAS ONLINE",
        "cluster": "Big Data"
    }
]